schmuck_inventar/__init__.py
schmuck_inventar/detection.py
schmuck_inventar/postprocessor.py
schmuck_inventar/recognition.py
schmuck_inventar/run.py
schmuck_inventar/utils.py
schmuck_inventar/config/regions.yaml
schmuck_inventar/resources/example_output.json
schmuck_inventar-0.1.4.dist-info/METADATA
schmuck_inventar-0.1.4.dist-info/WHEEL
schmuck_inventar-0.1.4.dist-info/entry_points.txt
schmuck_inventar-0.1.4.dist-info/top_level.txt
schmuck_inventar-0.1.4.dist-info/RECORD
